yaml2pyclass/__init__.py
yaml2pyclass/__version__.py
yaml2pyclass/code_generator.py
yaml2pyclass-0.1.2.dist-info/LICENSE
yaml2pyclass-0.1.2.dist-info/METADATA
yaml2pyclass-0.1.2.dist-info/WHEEL
yaml2pyclass-0.1.2.dist-info/top_level.txt
yaml2pyclass-0.1.2.dist-info/RECORD
