Metadata-Version: 2.1
Name: yaml2pyclass
Version: 0.1.2
Summary: Code generator that produces a Python class from a YAML input file. Can be used to facilitate code completion for config objects. 
Home-page: https://github.com/a-nau/yaml2pyclass
Author: Alexander Naumann, Felix Hertlein
Author-email: alex.code@mail.com, hertlein@fzi.de
License: BSD-3
Classifier: License :: OSI Approved :: BSD License
Classifier: Programming Language :: Python
Classifier: Programming Language :: Python :: 3
Classifier: Programming Language :: Python :: 3.7
Classifier: Programming Language :: Python :: 3.8
Classifier: Programming Language :: Python :: 3.9
Classifier: Programming Language :: Python :: 3.10
Classifier: Programming Language :: Python :: Implementation :: CPython
Classifier: Programming Language :: Python :: Implementation :: PyPy
Requires-Python: >=3.7.0
License-File: LICENSE
Requires-Dist: pyyaml
Provides-Extra: all
Requires-Dist: pyyaml ; extra == 'all'
Requires-Dist: black >=20.1.0 ; extra == 'all'
Requires-Dist: isort ==5.9.3 ; extra == 'all'
Requires-Dist: mypy >=0.761 ; extra == 'all'
Requires-Dist: pre-commit >=2.9.2 ; extra == 'all'
Requires-Dist: pytest >=4.5.0 ; extra == 'all'
Requires-Dist: pytest-cov >=2.6.1 ; extra == 'all'
Requires-Dist: pyupgrade >=3.2.0 ; extra == 'all'
Requires-Dist: types-PyYAML ; extra == 'all'
Requires-Dist: flask >=2.0.2 ; extra == 'all'
Requires-Dist: ipykernel >=6.9.0 ; extra == 'all'
Requires-Dist: mike >=0.5.3 ; extra == 'all'
Requires-Dist: mkdocs >=1.2.3 ; extra == 'all'
Requires-Dist: mkdocs-awesome-pages-plugin >=2.7.0 ; extra == 'all'
Requires-Dist: mkdocs-gen-files >=0.3.5 ; extra == 'all'
Requires-Dist: mkdocs-literate-nav >=0.4.1 ; extra == 'all'
Requires-Dist: mkdocs-material >=8.1.11 ; extra == 'all'
Requires-Dist: mkdocstrings[python] >=0.19.0 ; extra == 'all'
Requires-Dist: pytkdocs[numpy-style] >=0.5.0 ; extra == 'all'
Requires-Dist: ipython-genutils >=0.1.0 ; extra == 'all'
Requires-Dist: mkdocs-jupyter >=0.20.0 ; extra == 'all'
Requires-Dist: mkdocs-bibtex ==2.8.1 ; extra == 'all'
Requires-Dist: nbconvert ==6.4.2 ; extra == 'all'
Requires-Dist: numpydoc ==1.2 ; extra == 'all'
Requires-Dist: spacy ==3.2.2 ; extra == 'all'
Requires-Dist: jinja2 ==3.0.3 ; extra == 'all'
Provides-Extra: dev
Requires-Dist: pyyaml ; extra == 'dev'
Requires-Dist: black >=20.1.0 ; extra == 'dev'
Requires-Dist: isort ==5.9.3 ; extra == 'dev'
Requires-Dist: mypy >=0.761 ; extra == 'dev'
Requires-Dist: pre-commit >=2.9.2 ; extra == 'dev'
Requires-Dist: pytest >=4.5.0 ; extra == 'dev'
Requires-Dist: pytest-cov >=2.6.1 ; extra == 'dev'
Requires-Dist: pyupgrade >=3.2.0 ; extra == 'dev'
Requires-Dist: types-PyYAML ; extra == 'dev'
Provides-Extra: docs
Requires-Dist: flask >=2.0.2 ; extra == 'docs'
Requires-Dist: ipykernel >=6.9.0 ; extra == 'docs'
Requires-Dist: mike >=0.5.3 ; extra == 'docs'
Requires-Dist: mkdocs >=1.2.3 ; extra == 'docs'
Requires-Dist: mkdocs-awesome-pages-plugin >=2.7.0 ; extra == 'docs'
Requires-Dist: mkdocs-gen-files >=0.3.5 ; extra == 'docs'
Requires-Dist: mkdocs-literate-nav >=0.4.1 ; extra == 'docs'
Requires-Dist: mkdocs-material >=8.1.11 ; extra == 'docs'
Requires-Dist: mkdocstrings[python] >=0.19.0 ; extra == 'docs'
Requires-Dist: pytkdocs[numpy-style] >=0.5.0 ; extra == 'docs'
Requires-Dist: ipython-genutils >=0.1.0 ; extra == 'docs'
Requires-Dist: mkdocs-jupyter >=0.20.0 ; extra == 'docs'
Requires-Dist: mkdocs-bibtex ==2.8.1 ; extra == 'docs'
Requires-Dist: nbconvert ==6.4.2 ; extra == 'docs'
Requires-Dist: numpydoc ==1.2 ; extra == 'docs'
Requires-Dist: spacy ==3.2.2 ; extra == 'docs'
Requires-Dist: jinja2 ==3.0.3 ; extra == 'docs'
Provides-Extra: test
Requires-Dist: pyyaml ; extra == 'test'
Requires-Dist: black >=20.1.0 ; extra == 'test'
Requires-Dist: isort ==5.9.3 ; extra == 'test'
Requires-Dist: mypy >=0.761 ; extra == 'test'
Requires-Dist: pre-commit >=2.9.2 ; extra == 'test'
Requires-Dist: pytest >=4.5.0 ; extra == 'test'
Requires-Dist: pytest-cov >=2.6.1 ; extra == 'test'
Requires-Dist: pyupgrade >=3.2.0 ; extra == 'test'
Requires-Dist: types-PyYAML ; extra == 'test'
